peafowl_dox/__init__.py
peafowl_dox/exceptions.py
peafowl_dox/core/__init__.py
peafowl_dox/core/document_processor.py
peafowl_dox/core/image_utils.py
peafowl_dox/core/onedrive_provider.py
peafowl_dox/core/onedriver_provider.py
peafowl_dox/core/pdf_converter.py
peafowl_dox-0.3.1.dist-info/METADATA
peafowl_dox-0.3.1.dist-info/WHEEL
peafowl_dox-0.3.1.dist-info/top_level.txt
peafowl_dox-0.3.1.dist-info/RECORD
