Metadata-Version: 2.4
Name: peafowl-dox
Version: 0.3.1
Requires-Python: >=3.8
Requires-Dist: numpy>=2.2.6
Requires-Dist: pillow>=11.1.0
Requires-Dist: opencv-python>=4.8.0
Requires-Dist: pymupdf>=1.23.0
Requires-Dist: o365>=2.0.9
Dynamic: description
Dynamic: description-content-type
Dynamic: requires-dist
Dynamic: requires-python
